{
  "title": "Todos Reunidos na Casa de Deus",
  "key": "E",
  "sections": [
    {
      "type": "intro",
      "chords": [
        ["E", "A9", "E/G#", "D9", "A/C#"],
        ["E", "A/C#", "E/G#", "D9", "A9"]
      ]
    },
    {
      "type": "verse",
      "lines": [
        {
          "lyrics": ["TODOS", "REUNIDOS", "NA", "CASA", "DE", "DEUS"],
          "chords": [ "E", null, null, "A9", null, null ]
        },
        {
          "lyrics": ["COM", "CANTOS", "DE", "ALEGRIA", "E", "GRANDE", "LOUVOR"],
          "chords": ["E", null, null, null, null, "A9", "B9"]
        },
        {
          "lyrics": ["VAMOS", "CELEBRAR", "OS", "FEITOS", "DO", "SENHOR"],
          "chords": ["A9", null, null, "B9", null, null]
        }
      ]
    }
  ]
}
